mxrepo/__init__.py
mxrepo/_version.py
mxrepo/main.py
mxrepo-1.0.0.dist-info/METADATA
mxrepo-1.0.0.dist-info/WHEEL
mxrepo-1.0.0.dist-info/entry_points.txt
mxrepo-1.0.0.dist-info/licenses/LICENSE.md
mxrepo-1.0.0.dist-info/RECORD
