Metadata-Version: 2.4
Name: mxrepo
Version: 1.0.0
Summary: Helper script for working with multiple git repositories.
Project-URL: Homepage, https://github.com/mxstack/mxrepo
Project-URL: Bug Reports, https://github.com/mxstack/mxrepo/issues
Project-URL: Source, https://github.com/mxstack/mxrepo/tree/main
Author-email: MX Stack Developers <dev@bluedynamics.com>
License: BSD 2-Clause License
License-File: LICENSE.md
Keywords: deployment,development,git
Classifier: Intended Audience :: Developers
Classifier: License :: OSI Approved :: BSD License
Classifier: Operating System :: OS Independent
Classifier: Programming Language :: Python
Classifier: Programming Language :: Python :: 3.10
Classifier: Programming Language :: Python :: 3.11
Classifier: Programming Language :: Python :: 3.12
Classifier: Programming Language :: Python :: 3.13
Classifier: Programming Language :: Python :: 3.14
Classifier: Topic :: Software Development :: Build Tools
Requires-Python: >=3.10
Provides-Extra: test
Requires-Dist: pytest; extra == 'test'
Requires-Dist: pytest-cov; extra == 'test'
Requires-Dist: pytest-mock; extra == 'test'
